{
    "path": ["Documents", "My Directory"],
    "records": [
        {
            "name": "Consectetuer.png",
            "id": 21,
            "fileTimes": {
                "accessed": {
                    "year": 2023,
                    "day": 11,
                    "month": 10,
                    "hour": 5,
                    "minute": 48,
                    "second": 47
                },
                "modified": {
                    "year": 2023,
                    "day": 3,
                    "month": 10,
                    "hour": 0,
                    "minute": 13,
                    "second": 39
                },
                "created": {
                    "year": 2023,
                    "day": 13,
                    "month": 8,
                    "hour": 21,
                    "minute": 15,
                    "second": 45
                }
            },
            "inner": {
                "tag": "File",
                "size": 10105354364
            }
        },
        {
            "name": "Praesent.tiff",
            "id": 78,
            "fileTimes": {
                "accessed": {
                    "year": 2023,
                    "day": 8,
                    "month": 9,
                    "hour": 19,
                    "minute": 2,
                    "second": 52
                },
                "modified": {
                    "year": 2023,
                    "day": 8,
                    "month": 6,
                    "hour": 15,
                    "minute": 45,
                    "second": 57
                },
                "created": {
                    "year": 2023,
                    "day": 21,
                    "month": 2,
                    "hour": 2,
                    "minute": 1,
                    "second": 19
                }
            },
            "inner": {
                "tag": "File",
                "size": 9035852395
            }
        },
        {
            "name": "Ipsum.gif",
            "id": 40,
            "fileTimes": {
                "accessed": {
                    "year": 2023,
                    "day": 8,
                    "month": 4,
                    "hour": 3,
                    "minute": 3,
                    "second": 19
                },
                "modified": {
                    "year": 2023,
                    "day": 5,
                    "month": 6,
                    "hour": 0,
                    "minute": 9,
                    "second": 47
                },
                "created": {
                    "year": 2023,
                    "day": 9,
                    "month": 12,
                    "hour": 10,
                    "minute": 34,
                    "second": 49
                }
            },
            "inner": {
                "tag": "File",
                "size": 6840641796
            }
        },
        {
            "name": "Mauris.xls",
            "id": 4,
            "fileTimes": {
                "accessed": {
                    "year": 2023,
                    "day": 1,
                    "month": 9,
                    "hour": 21,
                    "minute": 58,
                    "second": 17
                },
                "modified": {
                    "year": 2023,
                    "day": 12,
                    "month": 12,
                    "hour": 4,
                    "minute": 44,
                    "second": 33
                },
                "created": {
                    "year": 2023,
                    "day": 18,
                    "month": 3,
                    "hour": 10,
                    "minute": 9,
                    "second": 22
                }
            },
            "inner": {
                "tag": "File",
                "size": 700408540
            }
        },
        {
            "name": "VenenatisTristique.mp3",
            "id": 25,
            "fileTimes": {
                "accessed": {
                    "year": 2023,
                    "day": 19,
                    "month": 10,
                    "hour": 1,
                    "minute": 46,
                    "second": 9
                },
                "modified": {
                    "year": 2023,
                    "day": 30,
                    "month": 1,
                    "hour": 22,
                    "minute": 39,
                    "second": 57
                },
                "created": {
                    "year": 2023,
                    "day": 31,
                    "month": 7,
                    "hour": 19,
                    "minute": 36,
                    "second": 12
                }
            },
            "inner": {
                "tag": "File",
                "size": 9396640854
            }
        },
        {
            "name": "LobortisConvallisTortor.ppt",
            "id": 17,
            "fileTimes": {
                "accessed": {
                    "year": 2023,
                    "day": 19,
                    "month": 6,
                    "hour": 11,
                    "minute": 56,
                    "second": 32
                },
                "modified": {
                    "year": 2023,
                    "day": 30,
                    "month": 8,
                    "hour": 0,
                    "minute": 36,
                    "second": 18
                },
                "created": {
                    "year": 2023,
                    "day": 23,
                    "month": 9,
                    "hour": 23,
                    "minute": 34,
                    "second": 40
                }
            },
            "inner": {
                "tag": "Directory",
                "entries": {}
            }
        },
        {
            "name": "TristiqueTortorEu.ppt",
            "id": 65,
            "fileTimes": {
                "accessed": {
                    "year": 2023,
                    "day": 7,
                    "month": 12,
                    "hour": 12,
                    "minute": 9,
                    "second": 55
                },
                "modified": {
                    "year": 2023,
                    "day": 1,
                    "month": 5,
                    "hour": 22,
                    "minute": 8,
                    "second": 53
                },
                "created": {
                    "year": 2023,
                    "day": 31,
                    "month": 3,
                    "hour": 19,
                    "minute": 7,
                    "second": 23
                }
            },
            "inner": {
                "tag": "Directory",
                "entries": {}
            }
        },
        {
            "name": "SapienSapien.xls",
            "id": 5,
            "fileTimes": {
                "accessed": {
                    "year": 2023,
                    "day": 26,
                    "month": 9,
                    "hour": 9,
                    "minute": 57,
                    "second": 29
                },
                "modified": {
                    "year": 2023,
                    "day": 25,
                    "month": 9,
                    "hour": 10,
                    "minute": 49,
                    "second": 52
                },
                "created": {
                    "year": 2023,
                    "day": 10,
                    "month": 7,
                    "hour": 3,
                    "minute": 11,
                    "second": 57
                }
            },
            "inner": {
                "tag": "Directory",
                "entries": {}
            }
        },
        {
            "name": "PedeJustoEu.mov",
            "id": 30,
            "fileTimes": {
                "accessed": {
                    "year": 2023,
                    "day": 1,
                    "month": 6,
                    "hour": 7,
                    "minute": 9,
                    "second": 7
                },
                "modified": {
                    "year": 2023,
                    "day": 16,
                    "month": 7,
                    "hour": 9,
                    "minute": 50,
                    "second": 30
                },
                "created": {
                    "year": 2023,
                    "day": 5,
                    "month": 2,
                    "hour": 9,
                    "minute": 55,
                    "second": 10
                }
            },
            "inner": {
                "tag": "Directory",
                "entries": {}
            }
        },
        {
            "name": "SemperInterdumMauris.xls",
            "id": 95,
            "fileTimes": {
                "accessed": {
                    "year": 2023,
                    "day": 31,
                    "month": 7,
                    "hour": 11,
                    "minute": 32,
                    "second": 31
                },
                "modified": {
                    "year": 2023,
                    "day": 15,
                    "month": 2,
                    "hour": 20,
                    "minute": 3,
                    "second": 15
                },
                "created": {
                    "year": 2023,
                    "day": 6,
                    "month": 3,
                    "hour": 11,
                    "minute": 28,
                    "second": 54
                }
            },
            "inner": {
                "tag": "Directory",
                "entries": {}
            }
        }
    ],
    "currDirRecord": {
        "name": "LobortisConvallisTortor.ppt",
        "id": 17,
        "fileTimes": {
            "accessed": {
                "year": 2023,
                "day": 19,
                "month": 6,
                "hour": 11,
                "minute": 56,
                "second": 32
            },
            "modified": {
                "year": 2023,
                "day": 30,
                "month": 8,
                "hour": 0,
                "minute": 36,
                "second": 18
            },
            "created": {
                "year": 2023,
                "day": 23,
                "month": 9,
                "hour": 23,
                "minute": 34,
                "second": 40
            }
        },
        "inner": {
            "tag": "Directory",
            "entries": {}
        }
    },
    "pinned": [
        {
            "name": "Consectetuer.png",
            "id": 21,
            "fileTimes": {
                "accessed": {
                    "year": 2023,
                    "day": 11,
                    "month": 10,
                    "hour": 5,
                    "minute": 48,
                    "second": 47
                },
                "modified": {
                    "year": 2023,
                    "day": 3,
                    "month": 10,
                    "hour": 0,
                    "minute": 13,
                    "second": 39
                },
                "created": {
                    "year": 2023,
                    "day": 13,
                    "month": 8,
                    "hour": 21,
                    "minute": 15,
                    "second": 45
                }
            },
            "inner": {
                "tag": "File",
                "size": 10105354364
            }
        },
        {
            "name": "Praesent.tiff",
            "id": 78,
            "fileTimes": {
                "accessed": {
                    "year": 2023,
                    "day": 8,
                    "month": 9,
                    "hour": 19,
                    "minute": 2,
                    "second": 52
                },
                "modified": {
                    "year": 2023,
                    "day": 8,
                    "month": 6,
                    "hour": 15,
                    "minute": 45,
                    "second": 57
                },
                "created": {
                    "year": 2023,
                    "day": 21,
                    "month": 2,
                    "hour": 2,
                    "minute": 1,
                    "second": 19
                }
            },
            "inner": {
                "tag": "File",
                "size": 9035852395
            }
        },
        {
            "name": "Ipsum.gif",
            "id": 40,
            "fileTimes": {
                "accessed": {
                    "year": 2023,
                    "day": 8,
                    "month": 4,
                    "hour": 3,
                    "minute": 3,
                    "second": 19
                },
                "modified": {
                    "year": 2023,
                    "day": 5,
                    "month": 6,
                    "hour": 0,
                    "minute": 9,
                    "second": 47
                },
                "created": {
                    "year": 2023,
                    "day": 9,
                    "month": 12,
                    "hour": 10,
                    "minute": 34,
                    "second": 49
                }
            },
            "inner": {
                "tag": "File",
                "size": 6840641796
            }
        },
        {
            "name": "Mauris.xls",
            "id": 4,
            "fileTimes": {
                "accessed": {
                    "year": 2023,
                    "day": 1,
                    "month": 9,
                    "hour": 21,
                    "minute": 58,
                    "second": 17
                },
                "modified": {
                    "year": 2023,
                    "day": 12,
                    "month": 12,
                    "hour": 4,
                    "minute": 44,
                    "second": 33
                },
                "created": {
                    "year": 2023,
                    "day": 18,
                    "month": 3,
                    "hour": 10,
                    "minute": 9,
                    "second": 22
                }
            },
            "inner": {
                "tag": "File",
                "size": 700408540
            }
        },
        {
            "name": "VenenatisTristique.mp3",
            "id": 25,
            "fileTimes": {
                "accessed": {
                    "year": 2023,
                    "day": 19,
                    "month": 10,
                    "hour": 1,
                    "minute": 46,
                    "second": 9
                },
                "modified": {
                    "year": 2023,
                    "day": 30,
                    "month": 1,
                    "hour": 22,
                    "minute": 39,
                    "second": 57
                },
                "created": {
                    "year": 2023,
                    "day": 31,
                    "month": 7,
                    "hour": 19,
                    "minute": 36,
                    "second": 12
                }
            },
            "inner": {
                "tag": "File",
                "size": 9396640854
            }
        }
    ]
}
